edx_ledger/__init__.py
edx_ledger/admin.py
edx_ledger/api.py
edx_ledger/apps.py
edx_ledger/models.py
edx_ledger/urls.py
edx_ledger/utils.py
edx_ledger/views.py
edx_ledger/migrations/0001_initial.py
edx_ledger/migrations/__init__.py
edx_ledger/templates/edx_ledger/base.html
edx_ledger-0.1.0.dist-info/LICENSE.txt
edx_ledger-0.1.0.dist-info/METADATA
edx_ledger-0.1.0.dist-info/WHEEL
edx_ledger-0.1.0.dist-info/top_level.txt
edx_ledger-0.1.0.dist-info/RECORD
