Metadata-Version: 2.1
Name: edx-ledger
Version: 0.1.0
Summary: Records transactions against a ledger, denominated in units of value.
Home-page: https://github.com/openedx/edx-ledger
Author: edX
Author-email: oscm@edx.org
License: AGPL 3.0
Keywords: Python edx
Platform: UNKNOWN
Classifier: Development Status :: 3 - Alpha
Classifier: Framework :: Django
Classifier: Framework :: Django :: 3.2
Classifier: Intended Audience :: Developers
Classifier: License :: OSI Approved :: GNU Affero General Public License v3 or later (AGPLv3+)
Classifier: Natural Language :: English
Classifier: Programming Language :: Python :: 3
Classifier: Programming Language :: Python :: 3.8
Requires-Python: >=3.8
License-File: LICENSE.txt
Requires-Dist: Django
Requires-Dist: django-extensions
Requires-Dist: django-filter
Requires-Dist: django-simple-history
Requires-Dist: djangoql
Requires-Dist: edx-django-release-util
Requires-Dist: edx-django-utils
Requires-Dist: edx-rbac
Requires-Dist: jsonfield2
Requires-Dist: mysqlclient
Requires-Dist: openedx-events
Requires-Dist: pytz
Requires-Dist: redis
Requires-Dist: rules
